{
  "version": "7",
  "dialect": "postgresql",
  "entries": [
    {
      "idx": 0,
      "version": "7",
      "when": 1765992732967,
      "tag": "0000_needy_secret_warriors",
      "breakpoints": true
    },
    {
      "idx": 1,
      "version": "7",
      "when": 1766294368925,
      "tag": "0001_wide_ironclad",
      "breakpoints": true
    },
    {
      "idx": 2,
      "version": "7",
      "when": 1766304568774,
      "tag": "0002_breezy_hulk",
      "breakpoints": true
    },
    {
      "idx": 3,
      "version": "7",
      "when": 1766304898168,
      "tag": "0003_bright_the_renegades",
      "breakpoints": true
    },
    {
      "idx": 4,
      "version": "7",
      "when": 1766306142434,
      "tag": "0004_yielding_invaders",
      "breakpoints": true
    },
    {
      "idx": 5,
      "version": "7",
      "when": 1766576975771,
      "tag": "0005_lovely_preak",
      "breakpoints": true
    }
  ]
}